gen3_util/__init__.py
gen3_util/config.yaml
gen3_util/util.py
gen3_util/access/__init__.py
gen3_util/access/cli.py
gen3_util/access/requestor.py
gen3_util/access/submitter.py
gen3_util/access/policies/__init__.py
gen3_util/access/policies/add-project-default.yaml
gen3_util/access/policies/add-user-read.yaml
gen3_util/access/policies/add-user-write.yaml
gen3_util/buckets/__init__.py
gen3_util/buckets/cli.py
gen3_util/buckets/lister.py
gen3_util/cli/__init__.py
gen3_util/cli/cli.py
gen3_util/cli/cloner.py
gen3_util/cli/committer.py
gen3_util/cli/common.py
gen3_util/cli/history.py
gen3_util/cli/initializer.py
gen3_util/cli/puller.py
gen3_util/cli/pusher.py
gen3_util/cli/status.py
gen3_util/common/__init__.py
gen3_util/config/__init__.py
gen3_util/config/cli.py
gen3_util/config/config.py
gen3_util/fhir/__init__.py
gen3_util/files/__init__.py
gen3_util/files/cli.py
gen3_util/files/downloader.py
gen3_util/files/lister.py
gen3_util/files/manifest.py
gen3_util/files/middleware.py
gen3_util/files/remover.py
gen3_util/files/uploader.py
gen3_util/jobs/__init__.py
gen3_util/jobs/cli.py
gen3_util/jobs/lister.py
gen3_util/meta/__init__.py
gen3_util/meta/bundler.py
gen3_util/meta/cli.py
gen3_util/meta/delta.py
gen3_util/meta/differ.py
gen3_util/meta/downloader.py
gen3_util/meta/importer.py
gen3_util/meta/lister.py
gen3_util/meta/publisher.py
gen3_util/meta/remover.py
gen3_util/meta/skeleton.py
gen3_util/meta/uploader.py
gen3_util/meta/validator.py
gen3_util/meta/tabular/__init__.py
gen3_util/projects/__init__.py
gen3_util/projects/cli.py
gen3_util/projects/creator.py
gen3_util/projects/lister.py
gen3_util/projects/remover.py
gen3_util/repo/__init__.py
gen3_util/repo/cli.py
gen3_util/repo/cloner.py
gen3_util/repo/committer.py
gen3_util/repo/history.py
gen3_util/repo/initializer.py
gen3_util/repo/puller.py
gen3_util/repo/pusher.py
gen3_util/repo/status.py
gen3_util/users/__init__.py
gen3_util/users/cli.py
tests/integration/__init__.py
tests/integration/conftest.py
gen3_util-0.0.16.dist-info/LICENSE
gen3_util-0.0.16.dist-info/METADATA
gen3_util-0.0.16.dist-info/WHEEL
gen3_util-0.0.16.dist-info/entry_points.txt
gen3_util-0.0.16.dist-info/top_level.txt
gen3_util-0.0.16.dist-info/RECORD
