Metadata-Version: 2.1
Name: gen3-util
Version: 0.0.16
Summary: Commons utilities
Home-page: https://github.com/ACED-IDP/gen3_util
Author: Ellrott Lab
Project-URL: Bug Reports, https://github.com/ACED-IDP/gen3_util/issues
Project-URL: Source, https://github.com/ACED-IDP/gen3_util
Keywords: gen3 bioinformatics
Classifier: Development Status :: 3 - Alpha
Classifier: Intended Audience :: Developers
Classifier: Topic :: Software Development :: Build Tools
Classifier: License :: OSI Approved :: MIT License
Classifier: Programming Language :: Python :: 3.9
Requires-Python: >=3.9, <4
License-File: LICENSE
Requires-Dist: gen3 ==4.22.2
Requires-Dist: click
Requires-Dist: orjson
Requires-Dist: inflection
Requires-Dist: tqdm >=4.61.2
Requires-Dist: requests
Requires-Dist: pydantic
Requires-Dist: pydantic-yaml
Requires-Dist: PyYAML >=6.0.1
Requires-Dist: diskcache
Requires-Dist: fhir.resources ==7.1.0
Requires-Dist: PyJWT ==2.8.0
Requires-Dist: deepmerge
Requires-Dist: flatten-json
Requires-Dist: nested-lookup
Requires-Dist: wcmatch
